Metadata-Version: 1.2
Name: tTodo
Version: 0.1
Summary: command-line todo tools to keeping the track of your tasks
Home-page: https://github.com/Epic-R-R/tTodo
Author: Sullivan Z
Author-email: salar.z@outlook.de
License: UNKNOWN
Keywords: todo,list,task,management,manager,track
Platform: UNKNOWN
Classifier: Development Status :: 3 - Alpha
Classifier: Intended Audience :: Developers
Classifier: Topic :: Software Development :: Build Tools
Classifier: License :: OSI Approved :: MIT License
Classifier: Programming Language :: Python :: 3
Classifier: Programming Language :: Python :: 3.4
Classifier: Programming Language :: Python :: 3.5
Classifier: Programming Language :: Python :: 3.6
Requires-Python: >=3.6
